gt521f32/__init__.py
gt521f32/gt521f32.py
gt521f32/interfaces/__init__.py
gt521f32/interfaces/exception.py
gt521f32/interfaces/scsi_linux.py
gt521f32/interfaces/scsi_windows.py
gt521f32/interfaces/serial.py
gt521f32/packets.py
gt521f32_viewer/__init__.py
gt521f32_viewer/__main__.py
gt521f32_viewer/viewer.py
pygt521f32-0.1.6.dist-info/LICENSE
pygt521f32-0.1.6.dist-info/WHEEL
pygt521f32-0.1.6.dist-info/METADATA
pygt521f32-0.1.6.dist-info/RECORD
