Metadata-Version: 2.1
Name: pygt521f32
Version: 0.1.6
Summary: An SDK module for the ADH-Tech GT521F32 fingerprint scanner
Author: Alon
Author-email: alonlivne@gmail.com
Requires-Python: >=3.8,<4.0
Classifier: Programming Language :: Python :: 3
Classifier: Programming Language :: Python :: 3.8
Classifier: Programming Language :: Python :: 3.9
Requires-Dist: Pillow (>=8.2.0,<9.0.0)
Requires-Dist: cython-sgio (>=1.1.2,<2.0.0); sys_platform == "linux"
Requires-Dist: pyserial (>=3.5,<4.0)
